{
  "kind": "collectionType",
  "collectionName": "landing_pages",
  "info": {
    "singularName": "landing-page",
    "pluralName": "landing-pages",
    "displayName": "landing-page",
    "description": ""
  },
  "options": {
    "draftAndPublish": true
  },
  "pluginOptions": {},
  "attributes": {
    "description": {
      "type": "richtext"
    },
    "image": {
      "type": "media",
      "multiple": false,
      "required": true,
      "allowedTypes": [
        "images"
      ]
    }
  }
}
